{
  "assets": {
    "horse_fin_flag3_64_sd_4_0": {
      "name": "horse_fin_flag3_64_sd_4_0",
      "x": 16,
      "y": -2,
      "exists": true
    },
    "horse_fin_flag3_64_a_4_0": {
      "name": "horse_fin_flag3_64_a_4_0",
      "x": 15,
      "y": 128,
      "exists": true
    },
    "horse_fin_flag3_64_b_4_0": {
      "name": "horse_fin_flag3_64_b_4_0",
      "x": -2,
      "y": 122,
      "exists": true
    },
    "horse_fin_flag3_64_b_4_1": {
      "name": "horse_fin_flag3_64_b_4_1",
      "x": -2,
      "y": 121,
      "exists": true
    },
    "horse_fin_flag3_64_b_4_2": {
      "name": "horse_fin_flag3_64_b_4_2",
      "x": -2,
      "y": 115,
      "exists": true
    },
    "horse_fin_flag3_64_b_4_3": {
      "name": "horse_fin_flag3_64_b_4_3",
      "x": -2,
      "y": 115,
      "exists": true
    },
    "horse_fin_flag3_32_sd_4_0": {
      "name": "horse_fin_flag3_32_sd_4_0",
      "x": 9,
      "y": -2,
      "exists": true
    },
    "horse_fin_flag3_32_a_4_0": {
      "name": "horse_fin_flag3_32_a_4_0",
      "x": 8,
      "y": 63,
      "exists": true
    },
    "horse_fin_flag3_32_b_4_0": {
      "name": "horse_fin_flag3_32_b_4_0",
      "x": -1,
      "y": 61,
      "exists": true
    },
    "horse_fin_flag3_32_b_4_1": {
      "name": "horse_fin_flag3_32_b_4_1",
      "x": -1,
      "y": 60,
      "exists": true
    },
    "horse_fin_flag3_32_b_4_2": {
      "name": "horse_fin_flag3_32_b_4_2",
      "x": -1,
      "y": 57,
      "exists": true
    },
    "horse_fin_flag3_32_b_4_3": {
      "name": "horse_fin_flag3_32_b_4_3",
      "x": -1,
      "y": 57,
      "exists": true
    },
    "horse_fin_flag3_icon_a": {
      "name": "horse_fin_flag3_icon_a",
      "x": 6,
      "y": 69,
      "exists": true
    },
    "horse_fin_flag3_64_sd_2_0": {
      "name": "horse_fin_flag3_64_sd_2_0",
      "flipH": 1,
      "source": "horse_fin_flag3_64_sd_4_0",
      "x": 16,
      "y": -2,
      "exists": false
    },
    "horse_fin_flag3_64_a_2_0": {
      "name": "horse_fin_flag3_64_a_2_0",
      "flipH": 1,
      "source": "horse_fin_flag3_64_a_4_0",
      "x": 15,
      "y": 128,
      "exists": false
    },
    "horse_fin_flag3_64_b_2_0": {
      "name": "horse_fin_flag3_64_b_2_0",
      "flipH": 1,
      "source": "horse_fin_flag3_64_b_4_0",
      "x": -2,
      "y": 122,
      "exists": false
    },
    "horse_fin_flag3_64_b_2_1": {
      "name": "horse_fin_flag3_64_b_2_1",
      "flipH": 1,
      "source": "horse_fin_flag3_64_b_4_1",
      "x": -2,
      "y": 121,
      "exists": false
    },
    "horse_fin_flag3_64_b_2_2": {
      "name": "horse_fin_flag3_64_b_2_2",
      "flipH": 1,
      "source": "horse_fin_flag3_64_b_4_2",
      "x": -2,
      "y": 115,
      "exists": false
    },
    "horse_fin_flag3_64_b_2_3": {
      "name": "horse_fin_flag3_64_b_2_3",
      "flipH": 1,
      "source": "horse_fin_flag3_64_b_4_3",
      "x": -2,
      "y": 115,
      "exists": false
    },
    "horse_fin_flag3_32_sd_2_0": {
      "name": "horse_fin_flag3_32_sd_2_0",
      "flipH": 1,
      "source": "horse_fin_flag3_32_sd_4_0",
      "x": 9,
      "y": -2,
      "exists": false
    },
    "horse_fin_flag3_32_a_2_0": {
      "name": "horse_fin_flag3_32_a_2_0",
      "flipH": 1,
      "source": "horse_fin_flag3_32_a_4_0",
      "x": 8,
      "y": 63,
      "exists": false
    },
    "horse_fin_flag3_32_b_2_0": {
      "name": "horse_fin_flag3_32_b_2_0",
      "flipH": 1,
      "source": "horse_fin_flag3_32_b_4_0",
      "x": -1,
      "y": 61,
      "exists": false
    },
    "horse_fin_flag3_32_b_2_1": {
      "name": "horse_fin_flag3_32_b_2_1",
      "flipH": 1,
      "source": "horse_fin_flag3_32_b_4_1",
      "x": -1,
      "y": 60,
      "exists": false
    },
    "horse_fin_flag3_32_b_2_2": {
      "name": "horse_fin_flag3_32_b_2_2",
      "flipH": 1,
      "source": "horse_fin_flag3_32_b_4_2",
      "x": -1,
      "y": 57,
      "exists": false
    },
    "horse_fin_flag3_32_b_2_3": {
      "name": "horse_fin_flag3_32_b_2_3",
      "flipH": 1,
      "source": "horse_fin_flag3_32_b_4_3",
      "x": -1,
      "y": 57,
      "exists": false
    }
  },
  "logic": {
    "dimensions": {
      "x": 1,
      "y": 1,
      "z": 1
    },
    "directions": [
      180,
      90
    ]
  },
  "visualization": {
    "1": {
      "angle": 360,
      "layerCount": 1,
      "size": 1,
      "directions": {}
    },
    "32": {
      "angle": 45,
      "layerCount": 2,
      "size": 32,
      "directions": {
        "2": [],
        "4": []
      },
      "animations": {
        "0": {
          "id": 0,
          "layers": [
            {
              "layerId": 0,
              "frameSequence": [
                [
                  0
                ]
              ]
            },
            {
              "layerId": 1,
              "frameSequence": [
                [
                  0,
                  1,
                  2,
                  3
                ]
              ]
            }
          ]
        }
      },
      "layers": [
        {
          "layerId": 0
        }
      ]
    },
    "64": {
      "angle": 45,
      "layerCount": 2,
      "size": 64,
      "directions": {
        "2": [],
        "4": []
      },
      "animations": {
        "0": {
          "id": 0,
          "layers": [
            {
              "layerId": 0,
              "frameSequence": []
            },
            {
              "layerId": 1,
              "frameSequence": [
                [
                  0,
                  1,
                  2,
                  3
                ]
              ]
            }
          ]
        }
      },
      "layers": [
        {
          "layerId": 0
        }
      ]
    }
  },
  "index": {
    "logic": "furniture_basic",
    "type": "horse_fin_flag3",
    "visualization": "furniture_animated"
  }
}